HTMLTestRunner.py
LICENSE
README.md
setup.py
caterpillar_HTMLTestRunner.egg-info/PKG-INFO
caterpillar_HTMLTestRunner.egg-info/SOURCES.txt
caterpillar_HTMLTestRunner.egg-info/dependency_links.txt
caterpillar_HTMLTestRunner.egg-info/top_level.txt