Metadata-Version: 2.1
Name: caterpillar-HTMLTestRunner
Version: 1.0.2
Summary: caterpillar_HTMLTestRunner
Home-page: https://gitee.com/redrose2020_admin/caterpillar_HTMLTestRunner
Author: redrose2100
Author-email: hitredrose@163.com
Maintainer: redrose2100
Maintainer-email: hitredrose@163.com
License: MIT License
Platform: all
Classifier: Development Status :: 4 - Beta
Classifier: Operating System :: OS Independent
Classifier: Intended Audience :: Developers
Classifier: License :: OSI Approved :: MIT License
Classifier: Programming Language :: Python
Classifier: Programming Language :: Python :: Implementation
Classifier: Programming Language :: Python :: 3
Classifier: Programming Language :: Python :: 3.5
Classifier: Programming Language :: Python :: 3.6
Classifier: Programming Language :: Python :: 3.7
Classifier: Programming Language :: Python :: 3.8
Classifier: Programming Language :: Python :: 3.9
Classifier: Topic :: Software Development :: Libraries
License-File: LICENSE
